co_simulations/__init__.py
co_simulations/factory/__init__.py
co_simulations/factory/simulation.py
co_simulations-0.1.0.dist-info/LICENSE
co_simulations-0.1.0.dist-info/METADATA
co_simulations-0.1.0.dist-info/WHEEL
co_simulations-0.1.0.dist-info/top_level.txt
co_simulations-0.1.0.dist-info/RECORD
